xenbridge/__init__.py
xenbridge/auth.py
xenbridge/blob.py
xenbridge/bond.py
xenbridge/certificate.py
xenbridge/cluster.py
xenbridge/cluster_host.py
xenbridge/console.py
xenbridge/crashdump.py
xenbridge/data_source.py
xenbridge/dr_task.py
xenbridge/event.py
xenbridge/feature.py
xenbridge/gpu_group.py
xenbridge/host.py
xenbridge/host_cpu.py
xenbridge/host_crashdump.py
xenbridge/host_metrics.py
xenbridge/host_patch.py
xenbridge/lvhd.py
xenbridge/message.py
xenbridge/network.py
xenbridge/network_sriov.py
xenbridge/pbd.py
xenbridge/pci.py
xenbridge/pgpu.py
xenbridge/pif.py
xenbridge/pif_metrics.py
xenbridge/pool.py
xenbridge/pool_patch.py
xenbridge/pool_update.py
xenbridge/probe_result.py
xenbridge/pusb.py
xenbridge/pvs_cache_storage.py
xenbridge/pvs_proxy.py
xenbridge/pvs_server.py
xenbridge/pvs_site.py
xenbridge/role.py
xenbridge/sdn_controller.py
xenbridge/secret.py
xenbridge/session.py
xenbridge/sm.py
xenbridge/sr.py
xenbridge/sr_stat.py
xenbridge/subject.py
xenbridge/task.py
xenbridge/tunnel.py
xenbridge/usb_group.py
xenbridge/user.py
xenbridge/vbd.py
xenbridge/vbd_metrics.py
xenbridge/vdi.py
xenbridge/vdi_nbd_server_info.py
xenbridge/vgpu.py
xenbridge/vgpu_type.py
xenbridge/vif.py
xenbridge/vif_metrics.py
xenbridge/vlan.py
xenbridge/vm.py
xenbridge/vm_appliance.py
xenbridge/vm_guest_metrics.py
xenbridge/vm_metrics.py
xenbridge/vmpp.py
xenbridge/vmss.py
xenbridge/vtpm.py
xenbridge/vusb.py
xenbridge/xenconnection.py
xenbridge/xenobject.py
xen_bridge-0.2.dist-info/LICENSE
xen_bridge-0.2.dist-info/METADATA
xen_bridge-0.2.dist-info/WHEEL
xen_bridge-0.2.dist-info/top_level.txt
xen_bridge-0.2.dist-info/RECORD
