Metadata-Version: 2.1
Name: xen-bridge
Version: 0.2
Summary: an object-oriented Xen API for python
Home-page: https://github.com/Frederic98/xen_bridge
Author: Frederic98
License: UNKNOWN
Platform: UNKNOWN
Classifier: Programming Language :: Python :: 3
Classifier: License :: OSI Approved :: GNU Lesser General Public License v3 or later (LGPLv3+)
Classifier: Operating System :: OS Independent
Requires-Python: >=3.8
License-File: LICENSE
